Metadata-Version: 1.0
Name: modbus
Version: 1
Summary: Modbus TCP Server and Client Programs
Home-page: https://github.com/ipal0/modbus
Author: Pal
Author-email: ipal0can@gmail.com
License: GPL
Platform: UNKNOWN
